{"success": true, "results": [{"date": "2021-03-15", "name": "Ae", "id": "USA_US-None", "total_count": 1, "lineage_count": 0, "cum_total_count": 1, "cum_lineage_count": 0, "proportion": 0.0, "proportion_ci_lower": 0.00038558098075590136, "proportion_ci_upper": 0.8532536836904249}, {"date": "2021-04-12", "name": "Alabama", "id": "USA_US-AL", "total_count": 4, "lineage_count": 0, "cum_total_count": 262, "cum_lineage_count": 2, "proportion": 0.007633587786259542, "proportion_ci_lower": 0.001589576610771804, "proportion_ci_upper": 0.024260891775430005}, {"date": "2021-04-15", "name": "Alaska", "id": "USA_US-AK", "total_count": 2, "lineage_count": 0, "cum_total_count": 422, "cum_lineage_count": 1, "proportion": 0.002369668246445498, "proportion_ci_lower": 0.00025580053002882263, "proportion_ci_upper": 0.01102169369933148}, {"date": "2021-04-15", "name": "Arizona", "id": "USA_US-AZ", "total_count": 2, "lineage_count": 0, "cum_total_count": 1955, "cum_lineage_count": 11, "proportion": 0.005626598465473146, "proportion_ci_lower": 0.0029929673282570635, "proportion_ci_upper": 0.009716752917911187}, {"date": "2021-04-09", "name": "Arkansas", "id": "USA_US-AR", "total_count": 3, "lineage_count": 0, "cum_total_count": 122, "cum_lineage_count": 0, "proportion": 0.0, "proportion_ci_lower": 4.016626137950731e-06, "proportion_ci_upper": 0.020337815909793455}, {"date": "2021-04-15", "name": "California", "id": "USA_US-CA", "total_count": 55, "lineage_count": 0, "cum_total_count": 11183, "cum_lineage_count": 14, "proportion": 0.0012519002056693195, "proportion_ci_lower": 0.0007176519225932618, "proportion_ci_upper": 0.002043420773266247}, {"date": "2021-04-13", "name": "Colorado", "id": "USA_US-CO", "total_count": 5, "lineage_count": 0, "cum_total_count": 4089, "cum_lineage_count": 3, "proportion": 0.0007336757153338225, "proportion_ci_lower": 0.00020667783031199104, "proportion_ci_upper": 0.001956711421735702}, {"date": "2021-04-17", "name": "Connecticut", "id": "USA_US-CT", "total_count": 8, "lineage_count": 0, "cum_total_count": 2396, "cum_lineage_count": 3, "proportion": 0.0012520868113522537, "proportion_ci_lower": 0.00035276568811971225, "proportion_ci_upper": 0.003337724171691203}, {"date": "2021-04-08", "name": "Delaware", "id": "USA_US-DE", "total_count": 1, "lineage_count": 0, "cum_total_count": 309, "cum_lineage_count": 0, "proportion": 0.0, "proportion_ci_lower": 1.5878221770297062e-06, "proportion_ci_upper": 0.008089786935683362}, {"date": "2021-04-13", "name": "District of Columbia", "id": "USA_US-DC", "total_count": 3, "lineage_count": 0, "cum_total_count": 179, "cum_lineage_count": 1, "proportion": 0.00558659217877095, "proportion_ci_lower": 0.0006034420501613088, "proportion_ci_upper": 0.02581056555395045}, {"date": "2021-04-19", "name": "Florida", "id": "USA_US-FL", "total_count": 1, "lineage_count": 0, "cum_total_count": 10300, "cum_lineage_count": 46, "proportion": 0.004466019417475728, "proportion_ci_lower": 0.003313058882334468, "proportion_ci_upper": 0.0058971467476938155}, {"date": "2021-03-10", "name": "GA", "id": "USA_US-None", "total_count": 1, "lineage_count": 0, "cum_total_count": 1, "cum_lineage_count": 0, "proportion": 0.0, "proportion_ci_lower": 0.00038558098075590136, "proportion_ci_upper": 0.8532536836904249}, {"date": "2021-04-13", "name": "Georgia", "id": "USA_US-GA", "total_count": 2, "lineage_count": 0, "cum_total_count": 1869, "cum_lineage_count": 9, "proportion": 0.004815409309791332, "proportion_ci_lower": 0.002385280475322529, "proportion_ci_upper": 0.008770115488518138}, {"date": "2021-04-12", "name": "Hawaii", "id": "USA_US-HI", "total_count": 1, "lineage_count": 0, "cum_total_count": 274, "cum_lineage_count": 0, "proportion": 0.0, "proportion_ci_lower": 1.7904609477253378e-06, "proportion_ci_upper": 0.009117489613295103}, {"date": "2021-04-09", "name": "Idaho", "id": "USA_US-ID", "total_count": 2, "lineage_count": 0, "cum_total_count": 363, "cum_lineage_count": 0, "proportion": 0.0, "proportion_ci_lower": 1.351780069846864e-06, "proportion_ci_upper": 0.006891331633948402}, {"date": "2021-04-15", "name": "Illinois", "id": "USA_US-IL", "total_count": 1, "lineage_count": 0, "cum_total_count": 4146, "cum_lineage_count": 16, "proportion": 0.003859141341051616, "proportion_ci_lower": 0.0022986505993601086, "proportion_ci_upper": 0.0061100750912445045}, {"date": "2021-04-12", "name": "Indiana", "id": "USA_US-IN", "total_count": 11, "lineage_count": 0, "cum_total_count": 1766, "cum_lineage_count": 35, "proportion": 0.019818799546998868, "proportion_ci_lower": 0.014079665638778837, "proportion_ci_upper": 0.027128454768131194}, {"date": "2021-04-12", "name": "Iowa", "id": "USA_US-IA", "total_count": 1, "lineage_count": 0, "cum_total_count": 257, "cum_lineage_count": 0, "proportion": 0.0, "proportion_ci_lower": 1.908780789116022e-06, "proportion_ci_upper": 0.009717067887357975}, {"date": "2021-04-21", "name": "Kansas", "id": "USA_US-KS", "total_count": 6, "lineage_count": 0, "cum_total_count": 513, "cum_lineage_count": 0, "proportion": 0.0, "proportion_ci_lower": 9.567155682947779e-07, "proportion_ci_upper": 0.004882231569106293}, {"date": "2021-04-09", "name": "Kentucky", "id": "USA_US-KY", "total_count": 1, "lineage_count": 0, "cum_total_count": 581, "cum_lineage_count": 7, "proportion": 0.012048192771084338, "proportion_ci_lower": 0.005404810569816867, "proportion_ci_upper": 0.023508863356991205}, {"date": "2021-04-15", "name": "Las Vegas", "id": "USA_US-None", "total_count": 1, "lineage_count": 0, "cum_total_count": 19, "cum_lineage_count": 0, "proportion": 0.0, "proportion_ci_lower": 2.5505812625695268e-05, "proportion_ci_upper": 0.12230940431991393}, {"date": "2021-04-12", "name": "Louisiana", "id": "USA_US-LA", "total_count": 3, "lineage_count": 0, "cum_total_count": 344, "cum_lineage_count": 0, "proportion": 0.0, "proportion_ci_lower": 1.4263880286386667e-06, "proportion_ci_upper": 0.007270294670444185}, {"date": "2021-04-14", "name": "Maine", "id": "USA_US-ME", "total_count": 5, "lineage_count": 0, "cum_total_count": 679, "cum_lineage_count": 55, "proportion": 0.08100147275405008, "proportion_ci_lower": 0.06225050040422415, "proportion_ci_upper": 0.10331367759390342}, {"date": "2021-04-19", "name": "Maryland", "id": "USA_US-MD", "total_count": 2, "lineage_count": 0, "cum_total_count": 3573, "cum_lineage_count": 4, "proportion": 0.001119507416736636, "proportion_ci_lower": 0.000378002002516523, "proportion_ci_upper": 0.002659777621834114}, {"date": "2021-04-15", "name": "Massachusetts", "id": "USA_US-MA", "total_count": 18, "lineage_count": 0, "cum_total_count": 4637, "cum_lineage_count": 11, "proportion": 0.0023722234203148586, "proportion_ci_lower": 0.0012609904643309346, "proportion_ci_upper": 0.004101852204403733}, {"date": "2021-04-14", "name": "Michigan", "id": "USA_US-MI", "total_count": 2, "lineage_count": 0, "cum_total_count": 7261, "cum_lineage_count": 27, "proportion": 0.00371849607492081, "proportion_ci_lower": 0.0025078463862475537, "proportion_ci_upper": 0.00532402494143458}, {"date": "2021-04-20", "name": "Minnesota", "id": "USA_US-MN", "total_count": 2, "lineage_count": 0, "cum_total_count": 6411, "cum_lineage_count": 8, "proportion": 0.0012478552487911402, "proportion_ci_lower": 0.0005901092626570635, "proportion_ci_upper": 0.0023532309189276956}, {"date": "2021-04-13", "name": "Mississippi", "id": "USA_US-MS", "total_count": 3, "lineage_count": 0, "cum_total_count": 294, "cum_lineage_count": 0, "proportion": 0.0, "proportion_ci_lower": 1.6687645593631604e-06, "proportion_ci_upper": 0.008500422092423063}, {"date": "2021-04-12", "name": "Missouri", "id": "USA_US-MO", "total_count": 2, "lineage_count": 0, "cum_total_count": 517, "cum_lineage_count": 0, "proportion": 0.0, "proportion_ci_lower": 9.49317096455117e-07, "proportion_ci_upper": 0.004844567900516558}, {"date": "2021-04-08", "name": "Montana", "id": "USA_US-MT", "total_count": 3, "lineage_count": 0, "cum_total_count": 200, "cum_lineage_count": 0, "proportion": 0.0, "proportion_ci_lower": 2.4521027404097352e-06, "proportion_ci_upper": 0.012465661135917114}, {"date": "2021-04-20", "name": "Nebraska", "id": "USA_US-NE", "total_count": 2, "lineage_count": 0, "cum_total_count": 349, "cum_lineage_count": 0, "proportion": 0.0, "proportion_ci_lower": 1.4059673229917557e-06, "proportion_ci_upper": 0.007166584288632896}, {"date": "2021-04-19", "name": "Nevada", "id": "USA_US-NV", "total_count": 5, "lineage_count": 0, "cum_total_count": 553, "cum_lineage_count": 0, "proportion": 0.0, "proportion_ci_lower": 8.875450348511703e-07, "proportion_ci_upper": 0.004530046983653619}, {"date": "2021-04-13", "name": "New Hampshire", "id": "USA_US-NH", "total_count": 1, "lineage_count": 0, "cum_total_count": 589, "cum_lineage_count": 3, "proportion": 0.0050933786078098476, "proportion_ci_lower": 0.0014365443007344544, "proportion_ci_upper": 0.013529777751315364}, {"date": "2021-04-17", "name": "New Jersey", "id": "USA_US-NJ", "total_count": 11, "lineage_count": 0, "cum_total_count": 5628, "cum_lineage_count": 7, "proportion": 0.0012437810945273632, "proportion_ci_lower": 0.0005565043604804618, "proportion_ci_upper": 0.0024405387960493297}, {"date": "2021-04-12", "name": "New Mexico", "id": "USA_US-NM", "total_count": 1, "lineage_count": 0, "cum_total_count": 585, "cum_lineage_count": 0, "proportion": 0.0, "proportion_ci_lower": 8.390163311064284e-07, "proportion_ci_upper": 0.0042828867153572375}, {"date": "2021-04-22", "name": "New York", "id": "USA_US-NY", "total_count": 53, "lineage_count": 0, "cum_total_count": 15056, "cum_lineage_count": 0, "proportion": 0.0, "proportion_ci_lower": 3.261333668775362e-08, "proportion_ci_upper": 0.00016682331666734103}, {"date": "2021-04-15", "name": "North Carolina", "id": "USA_US-NC", "total_count": 2, "lineage_count": 0, "cum_total_count": 2202, "cum_lineage_count": 13, "proportion": 0.005903723887375113, "proportion_ci_lower": 0.003313050766863161, "proportion_ci_upper": 0.009787758923533896}, {"date": "2021-04-11", "name": "North Dakota", "id": "USA_US-ND", "total_count": 3, "lineage_count": 0, "cum_total_count": 265, "cum_lineage_count": 0, "proportion": 0.0, "proportion_ci_lower": 1.8512116339850463e-06, "proportion_ci_upper": 0.009425385197218375}, {"date": "2021-03-18", "name": "North Dalota", "id": "USA_US-None", "total_count": 1, "lineage_count": 0, "cum_total_count": 1, "cum_lineage_count": 0, "proportion": 0.0, "proportion_ci_lower": 0.00038558098075590136, "proportion_ci_upper": 0.8532536836904249}, {"date": "2021-04-15", "name": "Ohio", "id": "USA_US-OH", "total_count": 193, "lineage_count": 0, "cum_total_count": 2693, "cum_lineage_count": 17, "proportion": 0.0063126624582250275, "proportion_ci_lower": 0.0038234630347074956, "proportion_ci_upper": 0.00985955164788721}, {"date": "2021-04-13", "name": "Oklahoma", "id": "USA_US-OK", "total_count": 1, "lineage_count": 0, "cum_total_count": 130, "cum_lineage_count": 0, "proportion": 0.0, "proportion_ci_lower": 3.7699249767690984e-06, "proportion_ci_upper": 0.019100681880484}, {"date": "2021-04-19", "name": "Oregon", "id": "USA_US-OR", "total_count": 2, "lineage_count": 0, "cum_total_count": 735, "cum_lineage_count": 0, "proportion": 0.0, "proportion_ci_lower": 6.678468088749387e-07, "proportion_ci_upper": 0.0034106176512470683}, {"date": "2021-04-16", "name": "Pennsylvania", "id": "USA_US-PA", "total_count": 1, "lineage_count": 0, "cum_total_count": 5250, "cum_lineage_count": 20, "proportion": 0.0038095238095238095, "proportion_ci_lower": 0.0024029614186557875, "proportion_ci_upper": 0.005761750753082273}, {"date": "2021-04-12", "name": "Puerto Rico", "id": "USA_US-None", "total_count": 2, "lineage_count": 0, "cum_total_count": 251, "cum_lineage_count": 0, "proportion": 0.0, "proportion_ci_lower": 1.9543635247695973e-06, "proportion_ci_upper": 0.009947958654992832}, {"date": "2021-04-15", "name": "Rhode Island", "id": "USA_US-RI", "total_count": 1, "lineage_count": 0, "cum_total_count": 975, "cum_lineage_count": 0, "proportion": 0.0, "proportion_ci_lower": 5.034959434323717e-07, "proportion_ci_upper": 0.002572376984320068}, {"date": "2021-04-10", "name": "South Carolina", "id": "USA_US-SC", "total_count": 1, "lineage_count": 0, "cum_total_count": 359, "cum_lineage_count": 3, "proportion": 0.008356545961002786, "proportion_ci_lower": 0.0023590251807143344, "proportion_ci_upper": 0.02213147655375547}, {"date": "2021-04-06", "name": "South Dakota", "id": "USA_US-SD", "total_count": 3, "lineage_count": 0, "cum_total_count": 167, "cum_lineage_count": 0, "proportion": 0.0, "proportion_ci_lower": 2.9359240001471787e-06, "proportion_ci_upper": 0.014906823511655653}, {"date": "2021-04-12", "name": "Tennessee", "id": "USA_US-TN", "total_count": 9, "lineage_count": 0, "cum_total_count": 1265, "cum_lineage_count": 7, "proportion": 0.005533596837944664, "proportion_ci_lower": 0.002478457198610949, "proportion_ci_upper": 0.010833890575512872}, {"date": "2021-04-17", "name": "Texas", "id": "USA_US-TX", "total_count": 6, "lineage_count": 0, "cum_total_count": 5585, "cum_lineage_count": 9, "proportion": 0.0016114592658907788, "proportion_ci_lower": 0.0007976495438841028, "proportion_ci_upper": 0.0029390347317540533}, {"date": "2021-04-10", "name": "Unknown", "id": "USA_US-None", "total_count": 12, "lineage_count": 0, "cum_total_count": 41, "cum_lineage_count": 0, "proportion": 0.0, "proportion_ci_lower": 1.1903578569170632e-05, "proportion_ci_upper": 0.05907570990931319}, {"date": "2021-04-13", "name": "Utah", "id": "USA_US-UT", "total_count": 1, "lineage_count": 0, "cum_total_count": 369, "cum_lineage_count": 1, "proportion": 0.0027100271002710027, "proportion_ci_lower": 0.0002925610856198375, "proportion_ci_upper": 0.01259581565970369}, {"date": "2021-04-10", "name": "Vermont", "id": "USA_US-VT", "total_count": 1, "lineage_count": 0, "cum_total_count": 291, "cum_lineage_count": 0, "proportion": 0.0, "proportion_ci_lower": 1.6859535234383486e-06, "proportion_ci_upper": 0.008587602885325165}, {"date": "2021-04-16", "name": "Virginia", "id": "USA_US-VA", "total_count": 7, "lineage_count": 0, "cum_total_count": 1537, "cum_lineage_count": 20, "proportion": 0.013012361743656473, "proportion_ci_lower": 0.008220995307607263, "proportion_ci_upper": 0.019631767376860676}, {"date": "2021-04-21", "name": "Washington", "id": "USA_US-WA", "total_count": 1, "lineage_count": 0, "cum_total_count": 4839, "cum_lineage_count": 18, "proportion": 0.0037197768133911966, "proportion_ci_lower": 0.002285634896104977, "proportion_ci_upper": 0.0057458693988815535}, {"date": "2021-04-17", "name": "West Virginia", "id": "USA_US-WV", "total_count": 1, "lineage_count": 0, "cum_total_count": 1594, "cum_lineage_count": 6, "proportion": 0.0037641154328732747, "proportion_ci_lower": 0.0015726050643033766, "proportion_ci_upper": 0.007742268750926762}, {"date": "2021-04-20", "name": "Wisconsin", "id": "USA_US-WI", "total_count": 2, "lineage_count": 0, "cum_total_count": 2359, "cum_lineage_count": 3, "proportion": 0.001271725307333616, "proportion_ci_lower": 0.0003583006237359106, "proportion_ci_upper": 0.0033900139777945926}, {"date": "2021-04-17", "name": "Wyoming", "id": "USA_US-WY", "total_count": 2, "lineage_count": 0, "cum_total_count": 347, "cum_lineage_count": 0, "proportion": 0.0, "proportion_ci_lower": 1.4140650370424514e-06, "proportion_ci_upper": 0.007207711343976978}]}